README.rst
setup.py
myhdl_tools/_SignalQueue.py
myhdl_tools/__init__.py
myhdl_tools/_altera.py
myhdl_tools/_fpga.py
myhdl_tools/_get_args.py
myhdl_tools/_mysigs.py
myhdl_tools/_simulators.py
myhdl_tools/_xilinx.py
myhdl_tools.egg-info/PKG-INFO
myhdl_tools.egg-info/SOURCES.txt
myhdl_tools.egg-info/dependency_links.txt
myhdl_tools.egg-info/top_level.txt
myhdl_tools/boards/__init__.py
myhdl_tools/boards/_board_list.py
myhdl_tools/boards/_xboard_list.py
myhdl_tools/boards/xilinx/__init__.py
myhdl_tools/boards/xilinx/_atlys.py
myhdl_tools/boards/xilinx/_nexys.py
myhdl_tools/boards/xilinx/_papilio.py
myhdl_tools/boards/xilinx/_sx1.py
myhdl_tools/boards/xilinx/_ufo400.py
myhdl_tools/boards/xilinx/_xula.py
myhdl_tools/boards/xilinx/_xupv2p.py
test/test_clock.py
test/test_fpga_flow.py
test/test_reset.py