Metadata-Version: 1.0
Name: myhdl-tools
Version: 0.0.3
Summary: random collection of tools to support myhdl
Home-page: https://bitbucket.org/cfelton/myhdl_tools
Author: Christopher Felton
Author-email: chris.felton@gmail.com
License: LGPL
Keywords: myhdl FPGA tools
Platform: UNKNOWN
